{"Exif":{"Lat":0,"Long":0,"Date":"2024-01-14T07:32:30-08:00","Tags":{"ApertureValue":2.800000335430107,"BrightnessValue|*imagemeta.rat[int32]":"26381/5811","CreateDate":"2024:01:14 07:32:30","DateTimeOriginal":"2024:01:14 07:32:30","ExposureCompensation|*imagemeta.rat[int32]":"0","ExposureTime|*imagemeta.rat[uint32]":"1/100","FNumber|*imagemeta.rat[uint32]":"14/5","FocalLengthIn35mmFormat|uint16":"77","FocalLength|*imagemeta.rat[uint32]":"9","ISO|uint16":"100","LensInfo":"2.220000028611935 9 1.7799999713880652 2.8","LensMake":"Apple","LensModel":"iPhone 14 Pro back triple camera 9mm f/2.8","Make":"Apple","Model":"iPhone 14 Pro","ModifyDate":"2024:02:26 17:35:00","OffsetTime":"-08:00","OffsetTimeDigitized":"-08:00","OffsetTimeOriginal":"-08:00","SceneType|uint8":"1","ShutterSpeedValue":0.010000001315418236,"Software":"17.3","SubSecTimeDigitized|int":"156","SubSecTimeOriginal|int":"156","SubjectArea":"2011 1518 2323 1333"}}}
